gleam/__init__.py
gleam/_version.py
gleam/example.py
gleam/src/__init__.py
gleam/src/beautify.py
gleam/src/config.py
gleam/src/json_viewer.py
pygleam-1.1.2.dist-info/METADATA
pygleam-1.1.2.dist-info/WHEEL
pygleam-1.1.2.dist-info/licenses/LICENSE
pygleam-1.1.2.dist-info/RECORD
