Metadata-Version: 2.4
Name: pygleam
Version: 1.1.2
Summary: A lightweight Python package for enhanced print statements with automatic JSON/DataFrame formatting and beautiful colors
License-File: LICENSE
Keywords: print,json,colors,formatting,terminal,debugging
Author: Navaneeth Penumarthi
Author-email: navaneeth.penumarthi@gmail.com
Requires-Python: >=3.8.1,<4.0.0
Classifier: Development Status :: 4 - Beta
Classifier: Intended Audience :: Developers
Classifier: License :: OSI Approved :: MIT License
Classifier: Operating System :: OS Independent
Classifier: Programming Language :: Python :: 3
Classifier: Programming Language :: Python :: 3.9
Classifier: Programming Language :: Python :: 3.10
Classifier: Programming Language :: Python :: 3.11
Classifier: Programming Language :: Python :: 3.12
Classifier: Programming Language :: Python :: 3.13
Classifier: Programming Language :: Python :: 3.14
Classifier: Programming Language :: Python :: 3.7
Classifier: Programming Language :: Python :: 3.8
Classifier: Topic :: Software Development :: Libraries :: Python Modules
Classifier: Topic :: System :: Logging
Classifier: Topic :: Terminals
Classifier: Topic :: Utilities
Project-URL: Bug Reports, https://github.com/yourusername/pygleam/issues
Project-URL: Documentation, https://github.com/yourusername/pygleam
Project-URL: Homepage, https://github.com/yourusername/pygleam
Project-URL: Repository, https://github.com/yourusername/pygleam
Project-URL: Source, https://github.com/yourusername/pygleam
